main.py
instead_of_pymysql-0.0.1.dist-info/METADATA
instead_of_pymysql-0.0.1.dist-info/WHEEL
instead_of_pymysql-0.0.1.dist-info/top_level.txt
instead_of_pymysql-0.0.1.dist-info/RECORD
