Metadata-Version: 2.1
Name: instead-of-pymysql
Version: 0.0.1
Summary: Instead of PyMySQL
Author: davek
Author-email: hwangdoyeouyu@gmail.com
Requires-Python: >=3.6
